namedlist.py
namedlist-1.8a3.dist-info/LICENSE.txt
namedlist-1.8a3.dist-info/METADATA
namedlist-1.8a3.dist-info/NOTICE
namedlist-1.8a3.dist-info/WHEEL
namedlist-1.8a3.dist-info/top_level.txt
namedlist-1.8a3.dist-info/RECORD
